<?xml version="1.0" encoding="utf-8"?>
<Maps>
  <Map Type="System" Name="AREA_LOW" Priority="0">
    <Line Name="Area 1" Pattern="Solid">
      +36.669722+140.596667/
      +36.669722+141.080000/
      +37.036389+141.146667/
      +36.669722+140.596667
    </Line>
    <Line Name="Area 2" Pattern="Solid">
      +37.986389+140.130000/
      +37.203056+140.146667/
      +37.853056+139.463333/
      +37.986389+140.130000
    </Line>
    <Line Name="Area 3_SFC-100" Pattern="Solid">
      +37.319722+139.496667/
      +36.936389+139.896667/
      +36.686389+139.863333/
      +36.153056+138.763611/
      +36.336389+138.413611/
      +37.319722+139.496667
    </Line>
    <Line Name="Area 3_SFC-080" Pattern="Solid">
      +36.686389+139.863333/
      +36.936389+139.896667/
      +36.786389+140.063333/
      +36.686389+139.863333
    </Line>
    <Line Name="Area 4_SFC-110" Pattern="Solid">
      +35.136666+138.580278/
      +35.105555+137.706945/
      +35.050555+137.686944/
      +34.936667+137.780278/
      +35.136666+138.580278
    </Line>
    <Line Name="Area 4_SFC-070" Pattern="Solid">
      +34.976389+137.649444/
      +34.921944+137.722222/
      +34.936667+137.780278/
      +35.050555+137.686944/
      +35.015698+137.671467/
      +34.976389+137.649444
    </Line>
    <Line Name="Area 4_SFC-060_1" Pattern="Solid">
      +35.080278+137.698611/
      +35.077209+137.653639/
      +35.065000+137.587778/
      +34.981111+137.652222/
      +35.015698+137.671467/
      +35.080278+137.698611
    </Line>
    <Line Name="Area 4_SFC-060_2" Pattern="Solid">
      +35.153333+138.996945/
      +35.136667+138.580278/
      +34.936667+137.780278/
      +34.921945+137.722222/
      +34.903333+137.746945/
      +34.889651+138.260040/
      +34.891976+138.266712/
      +34.895242+138.283939/
      +34.896001+138.301595/
      +34.894233+138.319143/
      +34.889989+138.336051/
      +34.887463+138.342091/
      +34.870000+138.996945/
      +35.153333+138.996945
    </Line>
    <Line Name="Area 4_SFC-040" Pattern="Solid">
      +35.052778+137.547222/
      +34.976389+137.649445/
      +34.981111+137.652222/
      +35.065000+137.587778/
      +35.064148+137.584785/
      +35.052778+137.547222
    </Line>
    <Line Name="Area 5" Pattern="Solid">
      +35.945833+136.103889/
      +35.718889+136.315000/
      +35.711052+136.308550/
      +35.618307+136.222954/
      +35.586945+136.198333/
      +35.603056+135.630556/
      +35.945833+136.103889
    </Line>
    <Line Name="Area 6" Pattern="Solid">
      +36.336389+135.080556/
      +36.076667+135.049445/
      +35.919722+134.553611/
      +35.919722+133.663889/
      +36.532222+133.663889/
      +36.426667+133.863333/
      +36.336389+133.997222/
      +36.336389+135.080556
    </Line>
    <Line Name="Area 7" Pattern="Solid">
      +35.103056+132.597500/
      +34.403333+132.130833/
      +34.403333+132.130833/
      +34.548889+131.876389/
      +34.548889+131.876389/
      +34.558126+131.892096/
      +34.558126+131.892096/
      +34.575946+131.915333/
      +34.575946+131.915333/
      +34.596812+131.934453/
      +34.596812+131.934453/
      +34.604167+131.940000/
      +34.604167+131.940000/
      +34.956111+132.175278/
      +34.956111+132.175278/
      +35.103056+132.597500
    </Line>
    <Line Name="Area 8_SFC-110" Pattern="Solid">
      +34.136667+130.664167/
      +34.336389+130.664167/
      +34.686389+130.880833/
      +34.353333+131.480833/
      +34.136667+130.664167
    </Line>
    <Line Name="Area 8_SFC-030" Pattern="Solid">
      +34.103333+130.664167/
      +34.136667+130.664167/
      +34.353333+131.480833/
      +34.336667+131.497500/
      +34.253333+131.430833/
      +34.103333+130.664167
    </Line>
    <Line Name="Area 9_SFC-090" Pattern="Solid">
      +34.721138+131.343985/
      +34.686389+130.880833/
      +34.419722+131.361667/
      +34.581945+131.498333/
      +34.586111+131.478889/
      +34.592409+131.456952/
      +34.604271+131.428625/
      +34.619995+131.403234/
      +34.639104+131.381551/
      +34.661017+131.364235/
      +34.685069+131.351813/
      +34.710527+131.344661/
      +34.721138+131.343985
    </Line>
    <Line Name="Area 9_SFC-110" Pattern="Solid">
      +34.548889+131.876389/
      +34.543896+131.865450/
      +34.533687+131.836205/
      +34.527809+131.805248/
      +34.526441+131.773520/
      +34.529626+131.741985/
      +34.531111+131.733611/
      +34.581945+131.498333/
      +34.419722+131.361667/
      +34.353333+131.480833/
      +34.336667+131.497500/
      +34.253333+131.430833/
      +34.403333+132.130833/
      +34.548889+131.876389
    </Line>
  </Map>
</Maps>
